setup.cfg
setup.py
openedoo/__init__.py
openedoo/config.py
openedoo/error.py
openedoo/route.py
openedoo/tables.py
openedoo/bin/openedoo-cli.py
openedoo/conf/__init__.py
openedoo/core/__init__.py
openedoo/core/db/__init__.py
openedoo/core/libs/__init__.py
openedoo/core/libs/command.py
openedoo/core/libs/get_modul.py
openedoo/core/libs/get_requirement.py
openedoo/core/libs/install_pip.py
openedoo/core/libs/tools.py
openedoo/core/management/__init__.py
openedoo/core/management/base.py
openedoo/core/management/templates.py
openedoo/core/management/commands/__init__.py
openedoo/core/management/commands/createproject.py
openedoo_test.egg-info/PKG-INFO
openedoo_test.egg-info/SOURCES.txt
openedoo_test.egg-info/dependency_links.txt
openedoo_test.egg-info/entry_points.txt
openedoo_test.egg-info/not-zip-safe
openedoo_test.egg-info/requires.txt
openedoo_test.egg-info/top_level.txt